{
  "project_info": {
    "project_number": "246132125680",
    "project_id": "notes-aca04",
    "storage_bucket": "notes-aca04.appspot.com"
  },
  "client": [
    {
      "client_info": {
        "mobilesdk_app_id": "1:246132125680:android:744398d1acc682a357f735",
        "android_client_info": {
          "package_name": "com.akayush1108.notes"
        }
      },
      "oauth_client": [
        {
          "client_id": "246132125680-fn5tj7149ihhfnv8ngfv5td71qtkiqh1.apps.googleusercontent.com",
          "client_type": 3
        }
      ],
      "api_key": [
        {
          "current_key": "AIzaSyCElSFSAA63_BN_OjRpfwTOFTMwdHMNvj4"
        }
      ],
      "services": {
        "appinvite_service": {
          "other_platform_oauth_client": [
            {
              "client_id": "246132125680-fn5tj7149ihhfnv8ngfv5td71qtkiqh1.apps.googleusercontent.com",
              "client_type": 3
            }
          ]
        }
      }
    }
  ],
  "configuration_version": "1"
}